
  [
    {"username":"root","encrypted_password":"x","uid":"0","gid":"0","gecos":"root","home":"/root","shell":"/bin/bash"},
    {"username":"daemon","encrypted_password":"x","uid":"1","gid":"1","gecos":"daemon","home":"/usr/sbin","shell":"/usr/sbin/nologin"},
    {"username":"bin","encrypted_password":"x","uid":"2","gid":"2","gecos":"bin","home":"/bin","shell":"/usr/sbin/nologin"},
    {"username":"sys","encrypted_password":"x","uid":"3","gid":"3","gecos":"sys","home":"/dev","shell":"/usr/sbin/nologin"},
    {"username":"sync","encrypted_password":"x","uid":"4","gid":"65534","gecos":"sync","home":"/bin","shell":"/bin/sync"},
    {"username":"games","encrypted_password":"x","uid":"5","gid":"60","gecos":"games","home":"/usr/games","shell":"/usr/sbin/nologin"},
    {"username":"man","encrypted_password":"x","uid":"6","gid":"12","gecos":"man","home":"/var/cache/man","shell":"/usr/sbin/nologin"},
    {"username":"lp","encrypted_password":"x","uid":"7","gid":"7","gecos":"lp","home":"/var/spool/lpd","shell":"/usr/sbin/nologin"},
    {"username":"mail","encrypted_password":"x","uid":"8","gid":"8","gecos":"mail","home":"/var/mail","shell":"/usr/sbin/nologin"},
    {"username":"news","encrypted_password":"x","uid":"9","gid":"9","gecos":"news","home":"/var/spool/news","shell":"/usr/sbin/nologin"},
    {"username":"uucp","encrypted_password":"x","uid":"10","gid":"10","gecos":"uucp","home":"/var/spool/uucp","shell":"/usr/sbin/nologin"},
    {"username":"proxy","encrypted_password":"x","uid":"13","gid":"13","gecos":"proxy","home":"/bin","shell":"/usr/sbin/nologin"},
    {"username":"www-data","encrypted_password":"x","uid":"33","gid":"33","gecos":"www-data","home":"/var/www","shell":"/usr/sbin/nologin"},
    {"username":"backup","encrypted_password":"x","uid":"34","gid":"34","gecos":"backup","home":"/var/backups","shell":"/usr/sbin/nologin"},
    {"username":"list","encrypted_password":"x","uid":"38","gid":"38","gecos":"Mailing List Manager","home":"/var/list","shell":"/usr/sbin/nologin"},
    {"username":"irc","encrypted_password":"x","uid":"39","gid":"39","gecos":"ircd","home":"/var/run/ircd","shell":"/usr/sbin/nologin"},
    {"username":"gnats","encrypted_password":"x","uid":"41","gid":"41","gecos":"Gnats Bug-Reporting System (admin)","home":"/var/lib/gnats","shell":"/usr/sbin/nologin"},
    {"username":"nobody","encrypted_password":"x","uid":"65534","gid":"65534","gecos":"nobody","home":"/nonexistent","shell":"/usr/sbin/nologin"},
    {"username":"libuuid","encrypted_password":"x","uid":"100","gid":"101","gecos":"","home":"/var/lib/libuuid","shell":""},
    {"username":"syslog","encrypted_password":"x","uid":"101","gid":"104","gecos":"","home":"/home/syslog","shell":"/bin/false"},
    {"username":"messagebus","encrypted_password":"x","uid":"102","gid":"106","gecos":"","home":"/var/run/dbus","shell":"/bin/false"},
    {"username":"landscape","encrypted_password":"x","uid":"103","gid":"109","gecos":"","home":"/var/lib/landscape","shell":"/bin/false"},
    {"username":"sshd","encrypted_password":"x","uid":"104","gid":"65534","gecos":"","home":"/var/run/sshd","shell":"/usr/sbin/nologin"},
    {"username":"pollinate","encrypted_password":"x","uid":"105","gid":"1","gecos":"","home":"/var/cache/pollinate","shell":"/bin/false"},
    {"username":"vagrant","encrypted_password":"x","uid":"1000","gid":"1000","gecos":"","home":"/home/vagrant","shell":"/bin/bash"},
    {"username":"colord","encrypted_password":"x","uid":"106","gid":"112","gecos":"colord colour management daemon,,,","home":"/var/lib/colord","shell":"/bin/false"},
    {"username":"statd","encrypted_password":"x","uid":"107","gid":"65534","gecos":"","home":"/var/lib/nfs","shell":"/bin/false"},
    {"username":"puppet","encrypted_password":"x","uid":"108","gid":"114","gecos":"Puppet configuration management daemon,,,","home":"/var/lib/puppet","shell":"/bin/false"},
    {"username":"ubuntu","encrypted_password":"x","uid":"1001","gid":"1001","gecos":"Ubuntu","home":"/home/ubuntu","shell":"/bin/bash"},
    {"username":"mysql","encrypted_password":"x","uid":"109","gid":"116","gecos":"MySQL Server,,,","home":"/nonexistent","shell":"/bin/false"}
  ]
